Metadata-Version: 1.0
Name: OMS-distributions
Version: 0.1
Summary: Gaussian and Binomial distributions
Home-page: UNKNOWN
Author: Ori Slasky
Author-email: Orislasky@gmail.com
License: UNKNOWN
Platform: UNKNOWN
